{
  "synthetic_scene_id": "v4_14_18mo_42_001011",
  "duration_sec": 30.0,
  "sample_rate": 16000,
  "target_age_band": "14_18_months",
  "scene_type": "background_speech_negative",
  "target_child_present": false,
  "target_child_vocalized": false,
  "target_child_duration_sec": 0.0,
  "adult_present": true,
  "adult_duration_sec": 21.383114809049985,
  "non_target_child_present": false,
  "other_child_duration_sec": 0.0,
  "overlap_present": false,
  "max_overlap_speakers": 1,
  "mean_snr_db": 0.83,
  "rir_id": "Room030-00092",
  "noise_id": "noise-free-sound-0272",
  "generation_config_name": "v4_14_18mo",
  "generation_config_hash": "77bfdc3440a0",
  "random_seed": 1053,
  "source_segments": [
    {
      "speaker_label": "ADULT_0",
      "segment_id": "prov_adult_lily_011009_MOT_1463445_1465311",
      "source_dataset": "providence_adults",
      "start_sec": 0.0,
      "end_sec": 3.4787155462128294,
      "gain_db": 0.0,
      "rir_id": null
    },
    {
      "speaker_label": "ADULT_0",
      "segment_id": "playlogue_ADULT_ew_42ec_21135_392180_392820",
      "source_dataset": "playlogue_adults",
      "start_sec": 4.7611533662131915,
      "end_sec": 6.408492452416599,
      "gain_db": 0.0,
      "rir_id": null
    },
    {
      "speaker_label": "ADULT_0",
      "segment_id": "librispeech_8098-278278-0030",
      "source_dataset": "librispeech",
      "start_sec": 7.926671206457529,
      "end_sec": 8.93167307439209,
      "gain_db": 0.0,
      "rir_id": null
    },
    {
      "speaker_label": "ADULT_0",
      "segment_id": "librispeech_302-123516-0029",
      "source_dataset": "librispeech",
      "start_sec": 9.76271514290519,
      "end_sec": 12.739438964909784,
      "gain_db": 0.0,
      "rir_id": null
    },
    {
      "speaker_label": "ADULT_0",
      "segment_id": "prov_adult_alex_030119_MOT_1484943_1486623",
      "source_dataset": "providence_adults",
      "start_sec": 14.131378417750462,
      "end_sec": 17.171589873716226,
      "gain_db": 0.0,
      "rir_id": null
    },
    {
      "speaker_label": "ADULT_0",
      "segment_id": "prov_adult_lily_020701_MOT_2428050_2430041",
      "source_dataset": "providence_adults",
      "start_sec": 18.715054383524826,
      "end_sec": 21.13885556501257,
      "gain_db": 0.0,
      "rir_id": null
    },
    {
      "speaker_label": "ADULT_0",
      "segment_id": "librispeech_19-227-0062",
      "source_dataset": "librispeech",
      "start_sec": 22.257046076263606,
      "end_sec": 25.787376955540804,
      "gain_db": 0.0,
      "rir_id": null
    },
    {
      "speaker_label": "ADULT_0",
      "segment_id": "prov_adult_lily_010202_MOT_3030190_3032653",
      "source_dataset": "providence_adults",
      "start_sec": 26.103278692901842,
      "end_sec": 28.806148049548227,
      "gain_db": 0.0,
      "rir_id": null
    },
    {
      "speaker_label": "ADULT_0",
      "segment_id": "librispeech_332-128985-0061",
      "source_dataset": "librispeech",
      "start_sec": 29.421878386682497,
      "end_sec": 30.0,
      "gain_db": 0.0,
      "rir_id": null
    }
  ],
  "speakers": [
    "ADULT_0"
  ],
  "audio_path": "/orcd/scratch/orcd/008/manaal/child-adult-diarization/synth_results/synthetic_scenes_v4/wav/v4_14_18mo_42_001011.wav",
  "rttm_path": "/orcd/scratch/orcd/008/manaal/child-adult-diarization/synth_results/synthetic_scenes_v4/rttm/v4_14_18mo_42_001011.rttm"
}