{
  "synthetic_scene_id": "v4_14_18mo_42_001929",
  "duration_sec": 30.0,
  "sample_rate": 16000,
  "target_age_band": "14_18_months",
  "scene_type": "adult_only_negative",
  "target_child_present": false,
  "target_child_vocalized": false,
  "target_child_duration_sec": 0.0,
  "adult_present": true,
  "adult_duration_sec": 21.420624408732422,
  "non_target_child_present": false,
  "other_child_duration_sec": 0.0,
  "overlap_present": false,
  "max_overlap_speakers": 1,
  "mean_snr_db": 22.39,
  "rir_id": "Room029-00069",
  "noise_id": "noise-free-sound-0704",
  "generation_config_name": "v4_14_18mo",
  "generation_config_hash": "77bfdc3440a0",
  "random_seed": 1971,
  "source_segments": [
    {
      "speaker_label": "ADULT_0",
      "segment_id": "prov_adult_lily_010521_MOT_2939515_2941895",
      "source_dataset": "providence_adults",
      "start_sec": 0.0,
      "end_sec": 1.4709085292317294,
      "gain_db": 0.0,
      "rir_id": null
    },
    {
      "speaker_label": "ADULT_0",
      "segment_id": "playlogue_ADULT_ew_42pc_21135_93760_97460",
      "source_dataset": "playlogue_adults",
      "start_sec": 3.1314556267256917,
      "end_sec": 7.3122251493106,
      "gain_db": 0.0,
      "rir_id": null
    },
    {
      "speaker_label": "ADULT_0",
      "segment_id": "playlogue_ADULT_ew_42ec_22180_465140_467680",
      "source_dataset": "playlogue_adults",
      "start_sec": 8.351878036091174,
      "end_sec": 12.189653581894092,
      "gain_db": 0.0,
      "rir_id": null
    },
    {
      "speaker_label": "ADULT_0",
      "segment_id": "prov_adult_lily_010117_MOT_1753475_1755626",
      "source_dataset": "providence_adults",
      "start_sec": 13.458678145272495,
      "end_sec": 16.223158096879075,
      "gain_db": 0.0,
      "rir_id": null
    },
    {
      "speaker_label": "ADULT_0",
      "segment_id": "prov_adult_ethan_001121_MOT_3430786_3432341",
      "source_dataset": "providence_adults",
      "start_sec": 17.36503885710438,
      "end_sec": 19.971527237927432,
      "gain_db": 0.0,
      "rir_id": null
    },
    {
      "speaker_label": "ADULT_0",
      "segment_id": "playlogue_ADULT_gleason_father_olivia_1752920_1753540",
      "source_dataset": "playlogue_adults",
      "start_sec": 20.491658519468952,
      "end_sec": 23.253288069480973,
      "gain_db": 0.0,
      "rir_id": null
    },
    {
      "speaker_label": "ADULT_0",
      "segment_id": "playlogue_ADULT_cameron_aae_B7_58_51_PE_N22_631820_635600",
      "source_dataset": "playlogue_adults",
      "start_sec": 24.71905273709387,
      "end_sec": 27.54318158147033,
      "gain_db": 0.0,
      "rir_id": null
    },
    {
      "speaker_label": "ADULT_0",
      "segment_id": "prov_adult_lily_020623_MOT_2017956_2019824",
      "source_dataset": "providence_adults",
      "start_sec": 29.025555915705244,
      "end_sec": 30.0,
      "gain_db": 0.0,
      "rir_id": null
    }
  ],
  "speakers": [
    "ADULT_0"
  ],
  "audio_path": "/orcd/scratch/orcd/008/manaal/child-adult-diarization/synth_results/synthetic_scenes_v4/wav/v4_14_18mo_42_001929.wav",
  "rttm_path": "/orcd/scratch/orcd/008/manaal/child-adult-diarization/synth_results/synthetic_scenes_v4/rttm/v4_14_18mo_42_001929.rttm"
}