{
  "synthetic_scene_id": "v4_14_18mo_42_001697",
  "duration_sec": 30.0,
  "sample_rate": 16000,
  "target_age_band": "14_18_months",
  "scene_type": "positive",
  "target_child_present": true,
  "target_child_vocalized": true,
  "target_child_duration_sec": 6.318850055527528,
  "adult_present": true,
  "adult_duration_sec": 22.769666656411186,
  "non_target_child_present": false,
  "other_child_duration_sec": 0.0,
  "overlap_present": false,
  "max_overlap_speakers": 1,
  "mean_snr_db": 1.61,
  "rir_id": null,
  "noise_id": "noise-free-sound-0289",
  "generation_config_name": "v4_14_18mo",
  "generation_config_hash": "77bfdc3440a0",
  "random_seed": 1739,
  "source_segments": [
    {
      "speaker_label": "ADULT_0",
      "segment_id": "prov_adult_lily_020215a_MOT_112881_114363",
      "source_dataset": "providence_adults",
      "start_sec": 0.0,
      "end_sec": 1.6989531312718238,
      "gain_db": 0.0,
      "rir_id": null
    },
    {
      "speaker_label": "TARGET_CHILD",
      "segment_id": "prov_adult_lily_020011_MOT_948288_949951",
      "source_dataset": "cleese_childrenized_providence_adults",
      "start_sec": 1.766933419596837,
      "end_sec": 3.307349763700154,
      "gain_db": 0.0,
      "rir_id": null
    },
    {
      "speaker_label": "ADULT_0",
      "segment_id": "prov_adult_lily_020115_MOT_645413_648585",
      "source_dataset": "providence_adults",
      "start_sec": 3.3008583508677445,
      "end_sec": 5.9091983425413135,
      "gain_db": 0.0,
      "rir_id": null
    },
    {
      "speaker_label": "TARGET_CHILD",
      "segment_id": "playlogue_ADULT_gleason_mother_frank_495760_499039",
      "source_dataset": "cleese_childrenized_playlogue_adults",
      "start_sec": 6.035503034277295,
      "end_sec": 7.257808966496221,
      "gain_db": 0.0,
      "rir_id": null
    },
    {
      "speaker_label": "ADULT_0",
      "segment_id": "prov_adult_alex_020012_MOT_3181743_3183035",
      "source_dataset": "providence_adults",
      "start_sec": 7.312167216049673,
      "end_sec": 14.148973999756375,
      "gain_db": 0.0,
      "rir_id": null
    },
    {
      "speaker_label": "TARGET_CHILD",
      "segment_id": "playlogue_ADULT_gleason_father_isadora_825360_827840",
      "source_dataset": "cleese_childrenized_playlogue_adults",
      "start_sec": 14.182550769689891,
      "end_sec": 14.63023452731603,
      "gain_db": 0.0,
      "rir_id": null
    },
    {
      "speaker_label": "ADULT_0",
      "segment_id": "playlogue_ADULT_ew_42ec_11051_85260_85820",
      "source_dataset": "playlogue_adults",
      "start_sec": 14.75529065533145,
      "end_sec": 17.794747128966836,
      "gain_db": 0.0,
      "rir_id": null
    },
    {
      "speaker_label": "TARGET_CHILD",
      "segment_id": "playlogue_ADULT_ew_42ec_12011_710480_711040",
      "source_dataset": "cleese_childrenized_playlogue_adults",
      "start_sec": 17.806455201029532,
      "end_sec": 18.603640266411386,
      "gain_db": 0.0,
      "rir_id": null
    },
    {
      "speaker_label": "ADULT_0",
      "segment_id": "prov_adult_ethan_010315_MOT_3407930_3409634",
      "source_dataset": "providence_adults",
      "start_sec": 18.66258451701274,
      "end_sec": 20.803888568517486,
      "gain_db": 0.0,
      "rir_id": null
    },
    {
      "speaker_label": "TARGET_CHILD",
      "segment_id": "tinyvox_Providence_William_010427_2558061_2559780",
      "source_dataset": "tinyvox",
      "start_sec": 20.91091747940279,
      "end_sec": 21.460231763713463,
      "gain_db": 0.0,
      "rir_id": null
    },
    {
      "speaker_label": "ADULT_0",
      "segment_id": "librispeech_289-121652-0009",
      "source_dataset": "librispeech",
      "start_sec": 21.53338412827238,
      "end_sec": 21.633384128272382,
      "gain_db": 0.0,
      "rir_id": null
    },
    {
      "speaker_label": "TARGET_CHILD",
      "segment_id": "playlogue_CHI_ew_42ec_21097_356060_357560_14_18_months",
      "source_dataset": "playlogue",
      "start_sec": 21.722267574084125,
      "end_sec": 22.51093012993616,
      "gain_db": 0.0,
      "rir_id": null
    },
    {
      "speaker_label": "ADULT_0",
      "segment_id": "prov_adult_alex_020314_MOT_633858_634772",
      "source_dataset": "providence_adults",
      "start_sec": 22.606271981205833,
      "end_sec": 27.302602469043386,
      "gain_db": 0.0,
      "rir_id": null
    },
    {
      "speaker_label": "TARGET_CHILD",
      "segment_id": "prov_adult_lily_010313_MOT_871778_872591",
      "source_dataset": "cleese_childrenized_providence_adults",
      "start_sec": 27.307275440667514,
      "end_sec": 28.180557556702098,
      "gain_db": 0.0,
      "rir_id": null
    },
    {
      "speaker_label": "ADULT_0",
      "segment_id": "librispeech_4830-25898-0018",
      "source_dataset": "librispeech",
      "start_sec": 28.20623961929059,
      "end_sec": 28.4858577064413,
      "gain_db": 0.0,
      "rir_id": null
    },
    {
      "speaker_label": "TARGET_CHILD",
      "segment_id": "playlogue_CHI_gleason_mother_david_803220_803880_14_18_months",
      "source_dataset": "playlogue",
      "start_sec": 28.53763376320172,
      "end_sec": 28.63763376320172,
      "gain_db": 0.0,
      "rir_id": null
    },
    {
      "speaker_label": "ADULT_0",
      "segment_id": "prov_adult_lily_020428_MOT_2067415_2071105",
      "source_dataset": "providence_adults",
      "start_sec": 28.63114235036931,
      "end_sec": 30.0,
      "gain_db": 0.0,
      "rir_id": null
    }
  ],
  "speakers": [
    "ADULT_0",
    "TARGET_CHILD"
  ],
  "audio_path": "/orcd/scratch/orcd/008/manaal/child-adult-diarization/synth_results/synthetic_scenes_v4/wav/v4_14_18mo_42_001697.wav",
  "rttm_path": "/orcd/scratch/orcd/008/manaal/child-adult-diarization/synth_results/synthetic_scenes_v4/rttm/v4_14_18mo_42_001697.rttm"
}