{
  "synthetic_scene_id": "v4_14_18mo_42_001624",
  "duration_sec": 30.0,
  "sample_rate": 16000,
  "target_age_band": "14_18_months",
  "scene_type": "positive",
  "target_child_present": true,
  "target_child_vocalized": true,
  "target_child_duration_sec": 5.51668396750256,
  "adult_present": true,
  "adult_duration_sec": 15.164464780010944,
  "non_target_child_present": false,
  "other_child_duration_sec": 0.0,
  "overlap_present": false,
  "max_overlap_speakers": 1,
  "mean_snr_db": 23.17,
  "rir_id": null,
  "noise_id": "noise-free-sound-0761",
  "generation_config_name": "v4_14_18mo",
  "generation_config_hash": "77bfdc3440a0",
  "random_seed": 1666,
  "source_segments": [
    {
      "speaker_label": "ADULT_0",
      "segment_id": "prov_adult_ethan_010117_MOT_340905_342717",
      "source_dataset": "providence_adults",
      "start_sec": 0.0,
      "end_sec": 0.8690553631814035,
      "gain_db": 0.0,
      "rir_id": null
    },
    {
      "speaker_label": "TARGET_CHILD",
      "segment_id": "playlogue_CHI_gleason_mother_david_1426160_1426800_14_18_months",
      "source_dataset": "playlogue",
      "start_sec": 0.8625639503489939,
      "end_sec": 1.8723638873282296,
      "gain_db": 0.0,
      "rir_id": null
    },
    {
      "speaker_label": "ADULT_0",
      "segment_id": "prov_adult_lily_011126_MOT_241527_242859",
      "source_dataset": "providence_adults",
      "start_sec": 1.9880737103453276,
      "end_sec": 3.5483295876087233,
      "gain_db": 0.0,
      "rir_id": null
    },
    {
      "speaker_label": "TARGET_CHILD",
      "segment_id": "prov_adult_lily_010719_MOT_2928968_2930694",
      "source_dataset": "cleese_childrenized_providence_adults",
      "start_sec": 3.5418381747763137,
      "end_sec": 4.76979009750902,
      "gain_db": 0.0,
      "rir_id": null
    },
    {
      "speaker_label": "ADULT_0",
      "segment_id": "prov_adult_ethan_010620_MOT_1517635_1519846",
      "source_dataset": "providence_adults",
      "start_sec": 4.818634598322283,
      "end_sec": 8.434167835502592,
      "gain_db": 0.0,
      "rir_id": null
    },
    {
      "speaker_label": "TARGET_CHILD",
      "segment_id": "prov_adult_lily_020123_MOT_1429418_1433344",
      "source_dataset": "world_childrenized_providence_adults",
      "start_sec": 8.507900760208116,
      "end_sec": 9.567022104171258,
      "gain_db": 0.0,
      "rir_id": null
    },
    {
      "speaker_label": "ADULT_0",
      "segment_id": "prov_adult_alex_021122_MOT_2262502_2263732",
      "source_dataset": "providence_adults",
      "start_sec": 9.690017316925383,
      "end_sec": 10.90742622148524,
      "gain_db": 0.0,
      "rir_id": null
    },
    {
      "speaker_label": "TARGET_CHILD",
      "segment_id": "playlogue_CHI_vh_smithf_587980_589080_14_18_months",
      "source_dataset": "playlogue",
      "start_sec": 11.020904754799835,
      "end_sec": 12.19394737835194,
      "gain_db": 0.0,
      "rir_id": null
    },
    {
      "speaker_label": "ADULT_0",
      "segment_id": "prov_adult_lily_020201_MOT_1562820_1564720",
      "source_dataset": "providence_adults",
      "start_sec": 12.25546732171785,
      "end_sec": 12.456890802277922,
      "gain_db": 0.0,
      "rir_id": null
    },
    {
      "speaker_label": "TARGET_CHILD",
      "segment_id": "providence_lily_010611_780985_783980",
      "source_dataset": "providence",
      "start_sec": 12.450399389445511,
      "end_sec": 13.397167529720882,
      "gain_db": 0.0,
      "rir_id": null
    },
    {
      "speaker_label": "ADULT_0",
      "segment_id": "librispeech_2092-145706-0041",
      "source_dataset": "librispeech",
      "start_sec": 13.390676116888471,
      "end_sec": 17.273138328122954,
      "gain_db": 0.0,
      "rir_id": null
    },
    {
      "speaker_label": "TARGET_CHILD",
      "segment_id": "prov_adult_lily_010117_MOT_1737148_1740515",
      "source_dataset": "cleese_childrenized_providence_adults",
      "start_sec": 17.266646915290544,
      "end_sec": 17.366646915290545,
      "gain_db": 0.0,
      "rir_id": null
    },
    {
      "speaker_label": "ADULT_0",
      "segment_id": "prov_adult_lily_010521_MOT_2838850_2840045",
      "source_dataset": "providence_adults",
      "start_sec": 17.34644686053842,
      "end_sec": 21.164772566569845,
      "gain_db": 0.0,
      "rir_id": null
    }
  ],
  "speakers": [
    "ADULT_0",
    "TARGET_CHILD"
  ],
  "audio_path": "/orcd/scratch/orcd/008/manaal/child-adult-diarization/synth_results/synthetic_scenes_v4/wav/v4_14_18mo_42_001624.wav",
  "rttm_path": "/orcd/scratch/orcd/008/manaal/child-adult-diarization/synth_results/synthetic_scenes_v4/rttm/v4_14_18mo_42_001624.rttm"
}