{"gap_ratio": 0.7417624312010258, "word_count": 113, "covered_sec": 22.480000000000008, "words_per_sec": 1.2980803057955552, "clip_duration": 87.051625, "text": "See now Bobby's gotta do it. You better do it now. You gotta do that half thing in his face. You gotta do that. You gotta get on the movie action. He might be. You better get in his face and do it also. Booba. It's not so loud when you're that close to his face. Okay. Can you go on my lap? Because I think because he got my lap, kid. He's like, nope. Gotcha now. Gotcha now. Booba. I think that's probably the first diaper he's worn today that doesn't coordinate with his shirt. Have you noticed that, like, every other diaper had some kind of yellow in it? Yeah. Gotcha."}