{
  "synthetic_scene_id": "v3_perturb_14_18mo_42_000098",
  "duration_sec": 30.0,
  "sample_rate": 16000,
  "target_age_band": "14_18_months",
  "scene_type": "adult_only_negative",
  "target_child_present": false,
  "target_child_vocalized": false,
  "target_child_duration_sec": 0.0,
  "adult_present": true,
  "adult_duration_sec": 24.394357669442137,
  "non_target_child_present": false,
  "other_child_duration_sec": 0.0,
  "overlap_present": false,
  "max_overlap_speakers": 1,
  "mean_snr_db": 5.44,
  "rir_id": null,
  "noise_id": "noise-free-sound-0135",
  "generation_config_name": "v3_perturb_14_18mo",
  "generation_config_hash": "39ab9ae31841",
  "random_seed": 140,
  "source_segments": [
    {
      "speaker_label": "ADULT_0",
      "segment_id": "prov_adult_lily_010803_MOT_3351641_3353443",
      "source_dataset": "providence_adults",
      "start_sec": 0.0,
      "end_sec": 6.199853985477671,
      "gain_db": 0.0,
      "rir_id": null
    },
    {
      "speaker_label": "ADULT_0",
      "segment_id": "prov_adult_alex_020314_MOT_1132370_1134719",
      "source_dataset": "providence_adults",
      "start_sec": 7.741643783162335,
      "end_sec": 8.738215560096155,
      "gain_db": 0.0,
      "rir_id": null
    },
    {
      "speaker_label": "ADULT_0",
      "segment_id": "prov_adult_alex_020606_MOT_1806120_1807260",
      "source_dataset": "providence_adults",
      "start_sec": 9.667727531665491,
      "end_sec": 11.885716317825565,
      "gain_db": 0.0,
      "rir_id": null
    },
    {
      "speaker_label": "ADULT_0",
      "segment_id": "librispeech_3214-167607-0034",
      "source_dataset": "librispeech",
      "start_sec": 12.432630187083024,
      "end_sec": 12.532630187083024,
      "gain_db": 0.0,
      "rir_id": null
    },
    {
      "speaker_label": "ADULT_0",
      "segment_id": "librispeech_3607-29116-0019",
      "source_dataset": "librispeech",
      "start_sec": 13.690635225545618,
      "end_sec": 17.9376263059926,
      "gain_db": 0.0,
      "rir_id": null
    },
    {
      "speaker_label": "ADULT_0",
      "segment_id": "librispeech_4340-15220-0063",
      "source_dataset": "librispeech",
      "start_sec": 18.581749071774205,
      "end_sec": 24.55070663218396,
      "gain_db": 0.0,
      "rir_id": null
    },
    {
      "speaker_label": "ADULT_0",
      "segment_id": "prov_adult_alex_010922_MOT_2532848_2537025",
      "source_dataset": "providence_adults",
      "start_sec": 24.865740415610745,
      "end_sec": 29.52973489562458,
      "gain_db": 0.0,
      "rir_id": null
    }
  ],
  "speakers": [
    "ADULT_0"
  ],
  "audio_path": "/orcd/scratch/orcd/008/manaal/child-adult-diarization/synth_results/synthetic_scenes_v3_perturb/wav/v3_perturb_14_18mo_42_000098.wav",
  "rttm_path": "/orcd/scratch/orcd/008/manaal/child-adult-diarization/synth_results/synthetic_scenes_v3_perturb/rttm/v3_perturb_14_18mo_42_000098.rttm"
}