{
  "synthetic_scene_id": "v3_perturb_14_18mo_42_000756",
  "duration_sec": 30.0,
  "sample_rate": 16000,
  "target_age_band": "14_18_months",
  "scene_type": "positive",
  "target_child_present": true,
  "target_child_vocalized": true,
  "target_child_duration_sec": 2.01183617785766,
  "adult_present": true,
  "adult_duration_sec": 11.390318130121607,
  "non_target_child_present": false,
  "other_child_duration_sec": 0.0,
  "overlap_present": false,
  "max_overlap_speakers": 1,
  "mean_snr_db": 21.93,
  "rir_id": "Room004-00029",
  "noise_id": "noise-free-sound-0510",
  "generation_config_name": "v3_perturb_14_18mo",
  "generation_config_hash": "39ab9ae31841",
  "random_seed": 798,
  "source_segments": [
    {
      "speaker_label": "ADULT_0",
      "segment_id": "playlogue_ADULT_ew_42ec_12056_117800_118119",
      "source_dataset": "playlogue_adults",
      "start_sec": 0.0,
      "end_sec": 5.092969248826233,
      "gain_db": 0.0,
      "rir_id": null
    },
    {
      "speaker_label": "TARGET_CHILD",
      "segment_id": "tinyvox_Providence_Ethan_010400_2523991_2526521",
      "source_dataset": "tinyvox",
      "start_sec": 5.8258797503696105,
      "end_sec": 6.59383204899018,
      "gain_db": 0.0,
      "rir_id": null
    },
    {
      "speaker_label": "ADULT_0",
      "segment_id": "prov_adult_lily_020201_MOT_526045_540246",
      "source_dataset": "providence_adults",
      "start_sec": 7.311104949929405,
      "end_sec": 10.49722510532034,
      "gain_db": 0.0,
      "rir_id": null
    },
    {
      "speaker_label": "TARGET_CHILD",
      "segment_id": "playlogue_CHI_vh_gardnerf_477980_478320_14_18_months",
      "source_dataset": "playlogue",
      "start_sec": 11.2437376826458,
      "end_sec": 11.653707344892174,
      "gain_db": 0.0,
      "rir_id": null
    },
    {
      "speaker_label": "ADULT_0",
      "segment_id": "prov_adult_lily_011009_MOT_656115_658026",
      "source_dataset": "providence_adults",
      "start_sec": 12.332274290157127,
      "end_sec": 15.443503016061566,
      "gain_db": 0.0,
      "rir_id": null
    },
    {
      "speaker_label": "TARGET_CHILD",
      "segment_id": "playlogue_CHI_gleason_father_ursula_203060_207420_14_18_months",
      "source_dataset": "playlogue",
      "start_sec": 16.61983223696055,
      "end_sec": 17.45374645395127,
      "gain_db": 0.0,
      "rir_id": null
    }
  ],
  "speakers": [
    "ADULT_0",
    "TARGET_CHILD"
  ],
  "audio_path": "/orcd/scratch/orcd/008/manaal/child-adult-diarization/synth_results/synthetic_scenes_v3_perturb/wav/v3_perturb_14_18mo_42_000756.wav",
  "rttm_path": "/orcd/scratch/orcd/008/manaal/child-adult-diarization/synth_results/synthetic_scenes_v3_perturb/rttm/v3_perturb_14_18mo_42_000756.rttm"
}