{
  "synthetic_scene_id": "v3_perturb_14_18mo_42_001052",
  "duration_sec": 30.0,
  "sample_rate": 16000,
  "target_age_band": "14_18_months",
  "scene_type": "adult_only_negative",
  "target_child_present": false,
  "target_child_vocalized": false,
  "target_child_duration_sec": 0.0,
  "adult_present": true,
  "adult_duration_sec": 24.947835035795283,
  "non_target_child_present": false,
  "other_child_duration_sec": 0.0,
  "overlap_present": false,
  "max_overlap_speakers": 1,
  "mean_snr_db": 15.69,
  "rir_id": null,
  "noise_id": "noise-free-sound-0490",
  "generation_config_name": "v3_perturb_14_18mo",
  "generation_config_hash": "39ab9ae31841",
  "random_seed": 1094,
  "source_segments": [
    {
      "speaker_label": "ADULT_0",
      "segment_id": "playlogue_ADULT_ew_42pc_22113_127400_128700",
      "source_dataset": "playlogue_adults",
      "start_sec": 0.0,
      "end_sec": 2.338284309816001,
      "gain_db": 0.0,
      "rir_id": null
    },
    {
      "speaker_label": "ADULT_0",
      "segment_id": "librispeech_4788-91208-0029",
      "source_dataset": "librispeech",
      "start_sec": 2.690956789223186,
      "end_sec": 5.526517681230106,
      "gain_db": 0.0,
      "rir_id": null
    },
    {
      "speaker_label": "ADULT_0",
      "segment_id": "prov_adult_alex_021011_MOT_159495_161086",
      "source_dataset": "providence_adults",
      "start_sec": 6.512600512411567,
      "end_sec": 10.586888334323024,
      "gain_db": 0.0,
      "rir_id": null
    },
    {
      "speaker_label": "ADULT_0",
      "segment_id": "librispeech_5390-30102-0007",
      "source_dataset": "librispeech",
      "start_sec": 11.018105704793697,
      "end_sec": 14.668887532712633,
      "gain_db": 0.0,
      "rir_id": null
    },
    {
      "speaker_label": "ADULT_0",
      "segment_id": "prov_adult_alex_010726_MOT_1976278_1979141",
      "source_dataset": "providence_adults",
      "start_sec": 15.058085941234536,
      "end_sec": 16.255862174442033,
      "gain_db": 0.0,
      "rir_id": null
    },
    {
      "speaker_label": "ADULT_0",
      "segment_id": "librispeech_2817-142371-0028",
      "source_dataset": "librispeech",
      "start_sec": 16.983985062478748,
      "end_sec": 20.17187216230096,
      "gain_db": 0.0,
      "rir_id": null
    },
    {
      "speaker_label": "ADULT_0",
      "segment_id": "prov_adult_alex_021108_MOT_860610_862553",
      "source_dataset": "providence_adults",
      "start_sec": 21.14253229808984,
      "end_sec": 26.50415977290072,
      "gain_db": 0.0,
      "rir_id": null
    },
    {
      "speaker_label": "ADULT_0",
      "segment_id": "playlogue_ADULT_ew_54ec_12015_398040_399340",
      "source_dataset": "playlogue_adults",
      "start_sec": 27.698370623698622,
      "end_sec": 30.0,
      "gain_db": 0.0,
      "rir_id": null
    }
  ],
  "speakers": [
    "ADULT_0"
  ],
  "audio_path": "/orcd/scratch/orcd/008/manaal/child-adult-diarization/synth_results/synthetic_scenes_v3_perturb/wav/v3_perturb_14_18mo_42_001052.wav",
  "rttm_path": "/orcd/scratch/orcd/008/manaal/child-adult-diarization/synth_results/synthetic_scenes_v3_perturb/rttm/v3_perturb_14_18mo_42_001052.rttm"
}