{
  "synthetic_scene_id": "v3_perturb_14_18mo_42_001481",
  "duration_sec": 30.0,
  "sample_rate": 16000,
  "target_age_band": "14_18_months",
  "scene_type": "adult_only_negative",
  "target_child_present": false,
  "target_child_vocalized": false,
  "target_child_duration_sec": 0.0,
  "adult_present": true,
  "adult_duration_sec": 22.82457581640757,
  "non_target_child_present": false,
  "other_child_duration_sec": 0.0,
  "overlap_present": false,
  "max_overlap_speakers": 1,
  "mean_snr_db": 17.76,
  "rir_id": "Room041-00057",
  "noise_id": "noise-free-sound-0809",
  "generation_config_name": "v3_perturb_14_18mo",
  "generation_config_hash": "39ab9ae31841",
  "random_seed": 1523,
  "source_segments": [
    {
      "speaker_label": "ADULT_0",
      "segment_id": "playlogue_ADULT_ew_42pc_12077_150160_152240",
      "source_dataset": "playlogue_adults",
      "start_sec": 0.0,
      "end_sec": 3.2065582058456203,
      "gain_db": 0.0,
      "rir_id": null
    },
    {
      "speaker_label": "ADULT_0",
      "segment_id": "playlogue_ADULT_gleason_father_laurel_995360_996340",
      "source_dataset": "playlogue_adults",
      "start_sec": 4.008347884712278,
      "end_sec": 4.74375176340981,
      "gain_db": 0.0,
      "rir_id": null
    },
    {
      "speaker_label": "ADULT_0",
      "segment_id": "playlogue_ADULT_ew_54ec_12077_660020_664180",
      "source_dataset": "playlogue_adults",
      "start_sec": 5.626649621649918,
      "end_sec": 7.62538378753298,
      "gain_db": 0.0,
      "rir_id": null
    },
    {
      "speaker_label": "ADULT_0",
      "segment_id": "playlogue_ADULT_ew_42pc_21135_64700_67000",
      "source_dataset": "playlogue_adults",
      "start_sec": 8.642044658506984,
      "end_sec": 13.068093253971783,
      "gain_db": 0.0,
      "rir_id": null
    },
    {
      "speaker_label": "ADULT_0",
      "segment_id": "playlogue_ADULT_gleason_mother_david_1043480_1046240",
      "source_dataset": "playlogue_adults",
      "start_sec": 13.955296033115706,
      "end_sec": 17.303934362469978,
      "gain_db": 0.0,
      "rir_id": null
    },
    {
      "speaker_label": "ADULT_0",
      "segment_id": "prov_adult_lily_020115_MOT_1834106_1834976",
      "source_dataset": "providence_adults",
      "start_sec": 18.017364475958264,
      "end_sec": 20.596088495777266,
      "gain_db": 0.0,
      "rir_id": null
    },
    {
      "speaker_label": "ADULT_0",
      "segment_id": "playlogue_ADULT_gleason_father_john_1212100_1214060",
      "source_dataset": "playlogue_adults",
      "start_sec": 21.783728202734988,
      "end_sec": 23.446228231002035,
      "gain_db": 0.0,
      "rir_id": null
    },
    {
      "speaker_label": "ADULT_0",
      "segment_id": "librispeech_1553-140048-0018",
      "source_dataset": "librispeech",
      "start_sec": 24.707582461106945,
      "end_sec": 28.634432897812943,
      "gain_db": 0.0,
      "rir_id": null
    },
    {
      "speaker_label": "ADULT_0",
      "segment_id": "librispeech_2836-5354-0016",
      "source_dataset": "librispeech",
      "start_sec": 29.05888184362976,
      "end_sec": 30.0,
      "gain_db": 0.0,
      "rir_id": null
    }
  ],
  "speakers": [
    "ADULT_0"
  ],
  "audio_path": "/orcd/scratch/orcd/008/manaal/child-adult-diarization/synth_results/synthetic_scenes_v3_perturb/wav/v3_perturb_14_18mo_42_001481.wav",
  "rttm_path": "/orcd/scratch/orcd/008/manaal/child-adult-diarization/synth_results/synthetic_scenes_v3_perturb/rttm/v3_perturb_14_18mo_42_001481.rttm"
}